muffinengine/__init__.py
muffinengine-0.0.2.dist-info/licenses/LICENSE
muffinengine-0.0.2.dist-info/METADATA
muffinengine-0.0.2.dist-info/WHEEL
muffinengine-0.0.2.dist-info/top_level.txt
muffinengine-0.0.2.dist-info/RECORD
